valve-range-query/__init__.py
valve-range-query/map_lib.py
valve-range-query/player_lib.py
valve-range-query/source_packet.py
valve_range_query-1.0.3.dist-info/DESCRIPTION.rst
valve_range_query-1.0.3.dist-info/METADATA
valve_range_query-1.0.3.dist-info/RECORD
valve_range_query-1.0.3.dist-info/WHEEL
valve_range_query-1.0.3.dist-info/metadata.json
valve_range_query-1.0.3.dist-info/top_level.txt
valverangequery/__init__.py
valverangequery/map_lib.py
valverangequery/player_lib.py
valverangequery/source_packet.py
