Metadata-Version: 2.0
Name: valve-range-query
Version: 1.0.3
Summary: Python library for Query of Valve Servers over a range of IPs
Home-page: https://github.com/anshulshah96/valve-range-query
Author: Anshul Shah
Author-email: anshulshah96@gmail.com
License: MIT
Keywords: valve query servers counter strike
Platform: UNKNOWN
Classifier: Development Status :: 4 - Beta
Classifier: Intended Audience :: Developers
Classifier: Topic :: Software Development :: Build Tools
Classifier: License :: OSI Approved :: MIT License
Classifier: Programming Language :: Python :: 2.7
